auto_ml/DataFrameVectorizer.py
auto_ml/__init__.py
auto_ml/_version.py
auto_ml/predictor.py
auto_ml/utils.py
auto_ml/utils_categorical_ensembling.py
auto_ml/utils_data_cleaning.py
auto_ml/utils_ensembling.py
auto_ml/utils_feature_selection.py
auto_ml/utils_model_training.py
auto_ml/utils_models.py
auto_ml/utils_scaling.py
auto_ml/utils_scoring.py
auto_ml-2.9.10.dist-info/DESCRIPTION.rst
auto_ml-2.9.10.dist-info/METADATA
auto_ml-2.9.10.dist-info/RECORD
auto_ml-2.9.10.dist-info/WHEEL
auto_ml-2.9.10.dist-info/metadata.json
auto_ml-2.9.10.dist-info/top_level.txt
