Metadata-Version: 1.1
Name: auto-ml
Version: 2.9.10
Summary: Automated machine learning for production and analytics
Home-page: https://github.com/ClimbsRocks/auto_ml
Author: Preston Parry
Author-email: ClimbsBytes@gmail.com
License: MIT
Keywords: machine learning,data science,automated machine learning,regressor,regressors,regression,classification,classifiers,classifier,estimators,predictors,XGBoost,Random Forest,sklearn,scikit-learn,analytics,analysts,coefficients,feature importancesanalytics,artificial intelligence,subpredictors,ensembling,stacking,blending,feature engineering,feature extraction,feature selection,production,pandas,dataframes,machinejs,deep learning,tensorflow,deeplearning,lightgbm,gradient boosting,gbm,keras
Platform: UNKNOWN
Classifier: Development Status :: 5 - Production/Stable
Classifier: Intended Audience :: Developers
Classifier: Intended Audience :: Information Technology
Classifier: Intended Audience :: Science/Research
Classifier: Topic :: Scientific/Engineering :: Artificial Intelligence
Classifier: Topic :: Scientific/Engineering :: Information Analysis
Classifier: Topic :: Software Development :: Libraries :: Python Modules
Classifier: License :: OSI Approved :: MIT License
Classifier: Programming Language :: Python :: 2
Classifier: Programming Language :: Python :: 2.7
Classifier: Programming Language :: Python :: 3
Classifier: Programming Language :: Python :: 3.4
Classifier: Programming Language :: Python :: 3.4
Classifier: Programming Language :: Python :: 3.6
